{"trial_id": "3", "hyperparameters": {"space": [{"class_name": "Int", "config": {"name": "units", "default": null, "conditions": [], "min_value": 32, "max_value": 512, "step": 32, "sampling": "linear"}}, {"class_name": "Choice", "config": {"name": "learning_rate", "default": 0.01, "conditions": [], "values": [0.01, 0.001, 0.0001], "ordered": true}}], "values": {"units": 224, "learning_rate": 0.01}}, "metrics": {"metrics": {"accuracy": {"direction": "max", "observations": [{"value": [0.9675416747728983], "step": 4}]}, "loss": {"direction": "min", "observations": [{"value": [0.12617206325133642], "step": 4}]}, "val_accuracy": {"direction": "max", "observations": [{"value": [0.9599722226460775], "step": 4}]}, "val_loss": {"direction": "min", "observations": [{"value": [0.20275579889615378], "step": 4}]}}}, "score": 0.9599722226460775, "best_step": 4, "status": "COMPLETED", "message": null}